{"Jayanagar 3rd Block": {"Marathahalli": []}, "Jayanagar 4th Block": {"Marathahalli": []}, "Bellandur": {"Marathahalli": ["330D", "340E", "340Q", "BC1", "V333W"]}, "Bellandur Railway Station": {"Marathahalli": ["327D", "327G", "327H", "330PG"]}, "Jayanagar 1st Block": {"Marathahalli": []}, "Chamarajpet": {"Marathahalli": []}, "Jayadeva Hospital": {"Marathahalli": ["329K", "411J", "V411K"]}, "BTM Layout Water Tank": {"Marathahalli": ["329K", "411J", "V411K"]}, "HAL Airport": {"Marathahalli": []}, "Domlur Bridge": {"Marathahalli": ["329K", "411J", "V411K", "V411L"]}, "K R Puram Railway Station": {"Marathahalli": ["500B", "502A", "504F", "MBS17"]}, "Bagmane Tech Park/LRDE": {"Marathahalli": ["504F"]}, "K R Puram": {"Marathahalli": ["340E", "504F"]}, "Domlur (Old Madras Road)": {"Marathahalli": []}, "Bannerghatta Mark Global School": {"Marathahalli": []}, "Bagmane Tech Park Junction": {"Marathahalli": ["314AA"]}, "BTM Layout 16th Main/Udupi Garden": {"Marathahalli": ["329K", "411J", "V411K"]}, "Bannerghatta National Park": {"Marathahalli": ["411J", "V411K"]}, "Garuda Mall": {"Marathahalli": ["248H", "304R", "306R", "322", "322B", "322C", "322D", "323", "323A", "323B", "323C", "323D", "323E", "323F", "323G", "323H", "323J", "323K", "323M", "323N", "324", "324A", "324B", "324C", "324D", "325", "325A", "326C", "326E", "327", "327A", "327B", "327C", "327D", "327E", "327F", "327G", "327H", "328", "328E", "328F", "328G", "328M", "329", "329A", "329B", "329C", "329E", "329F", "329H", "332", "333", "333B", "333D", "333E", "333F", "333G", "333H", "333K", "333L", "333M", "333N", "333Q", "333R"]}, "Banashankari": {"Marathahalli": ["329K"]}, "Electronic City BHEL/Siemens": {"Marathahalli": ["340Q"]}, "Marathahalli": {"Koramangala": []}, "Delmia Circle (J P Nagar 3rd Phase)": {"Marathahalli": []}, "Hebbal": {"Marathahalli": ["500B", "502A", "KIA6", "MBS2", "MBS17", "V402T"]}, "Koramangala": {"Marathahalli": []}, "Domlur": {"Marathahalli": ["248H", "304R", "306R", "320D", "322", "322B", "322C", "322D", "323", "323A", "323B", "323C", "323D", "323E", "323F", "323G", "323H", "323J", "323K", "323L", "323M", "323N", "324", "324A", "324B", "324C", "324D", "325", "325A", "326C", "326E", "327", "327A", "327B", "327C", "327D", "327E", "327F", "327G", "327H", "328", "328E", "328F", "328G", "328M", "329", "329A", "329B", "329C", "329D", "329E", "329F", "329G", "329H", "329J", "330", "330B", "330D", "330E", "330F", "330G", "330H", "330M", "330P"]}, "Electronic City Infosys Gate": {"Marathahalli": ["340Q"]}, "HSR Layout 17th Cross": {"Marathahalli": []}, "Kengeri": {"Marathahalli": []}, "Electronic City": {"Marathahalli": ["340Q", "411D"]}, "Bannerghatta Circle": {"Marathahalli": ["411J", "V411K"]}}